scafl/__init__.py
scafl/__main__.py
scafl/application.py
scafl/blacklist.py
scafl/main.py
scafl/settings.py
scafl/startup.py
scafl/steam_idle_proc.py
scafl/steam_user_badges.py
scafl/utils.py
scafl/gui/__init__.py
scafl/gui/about_dialog.py
scafl/gui/scafl_window.py
scafl/gui/steam_login_webview.py
scafl/gui/components/__init__.py
scafl/gui/components/badge_box.py
scafl/lib/libsteam_api32.so
scafl/lib64/libsteam_api64.so
scafl-0.4.1.dist-info/LICENSE
scafl-0.4.1.dist-info/METADATA
scafl-0.4.1.dist-info/WHEEL
scafl-0.4.1.dist-info/top_level.txt
scafl-0.4.1.dist-info/RECORD
