Metadata-Version: 2.1
Name: scafl
Version: 0.4.1
Summary: A Steam game idler for trading card drops
Home-page: https://github.com/DragonOfWar/scafl
Author: Dragon Of War
Author-email: therealdragonofwar@gmail.com
License: UNKNOWN
Project-URL: Bug Tracker, https://github.com/DragonOfWar/scafl/issues
Platform: UNKNOWN
Classifier: Programming Language :: Python :: 3
Classifier: License :: OSI Approved :: MIT License
Classifier: Operating System :: OS Independent
Requires-Python: >=3.6
License-File: LICENSE
Requires-Dist: beautifulsoup4 (==4.10.0)
Requires-Dist: requests (==2.26.0)
